LICENSE
README.md
setup.py
libcobblersignatures/__init__.py
libcobblersignatures/cli.py
libcobblersignatures/enums.py
libcobblersignatures/utils.py
libcobblersignatures.egg-info/PKG-INFO
libcobblersignatures.egg-info/SOURCES.txt
libcobblersignatures.egg-info/dependency_links.txt
libcobblersignatures.egg-info/entry_points.txt
libcobblersignatures.egg-info/requires.txt
libcobblersignatures.egg-info/top_level.txt
libcobblersignatures/models/__init__.py
libcobblersignatures/models/osbreed.py
libcobblersignatures/models/osversion.py
tests/__init__.py
tests/conftest.py
tests/test_osbreed.py
tests/test_osversion.py
tests/test_signatures.py