Metadata-Version: 2.1
Name: libcobblersignatures
Version: 0.0.1
Summary: This library manages the operating system distribution signatures to enable cobbler to detect it correctly.
Home-page: https://cobbler.github.io/
Author: Cobbler
Author-email: cobbler.project@gmail.com
Project-URL: Bug Reports, https://github.com/cobbler/cobbler/issues
Project-URL: Source, https://github.com/cobbler/cobbler
Keywords: cobbler
Classifier: Development Status :: 3 - Alpha
Classifier: Intended Audience :: Developers
Classifier: Topic :: Software Development :: Libraries
Classifier: License :: OSI Approved :: GNU General Public License v2 or later (GPLv2+)
Classifier: Programming Language :: Python :: 3
Classifier: Programming Language :: Python :: 3.5
Classifier: Programming Language :: Python :: 3.6
Classifier: Programming Language :: Python :: 3.7
Classifier: Programming Language :: Python :: 3.8
Requires-Python: >=3
Provides-Extra: docs
Provides-Extra: lint
Provides-Extra: test
License-File: LICENSE
